mcp_server_appwrite/__init__.py
mcp_server_appwrite/__main__.py
mcp_server_appwrite/server.py
mcp_server_appwrite/service.py
mcp_server_appwrite/tool_manager.py
mcp_server_appwrite-0.2.8.dist-info/METADATA
mcp_server_appwrite-0.2.8.dist-info/WHEEL
mcp_server_appwrite-0.2.8.dist-info/entry_points.txt
mcp_server_appwrite-0.2.8.dist-info/licenses/LICENSE
mcp_server_appwrite-0.2.8.dist-info/RECORD
