Metadata-Version: 2.4
Name: mcp-server-appwrite
Version: 0.2.8
Summary: MCP (Model Context Protocol) server for Appwrite
License-File: LICENSE
Requires-Python: >=3.12
Requires-Dist: appwrite>=13.4.1
Requires-Dist: docstring-parser>=0.16
Requires-Dist: mcp[cli]>=1.3.0
